colmap_wrapper/colmap/__init__.py
colmap_wrapper/colmap/bin.py
colmap_wrapper/colmap/camera.py
colmap_wrapper/colmap/colmap.py
colmap_wrapper/colmap/colmap_project.py
colmap_wrapper/colmap/utils.py
colmap_wrapper/data/__init__.py
colmap_wrapper/data/download.py
colmap_wrapper/visualization/__init__.py
colmap_wrapper/visualization/visualization.py
colmap_wrapper/visualization/visualization_photogrammetry_software.py
colmap_wrapper-1.1.5.dist-info/LICENSE
colmap_wrapper-1.1.5.dist-info/METADATA
colmap_wrapper-1.1.5.dist-info/WHEEL
colmap_wrapper-1.1.5.dist-info/top_level.txt
colmap_wrapper-1.1.5.dist-info/RECORD
