Metadata-Version: 2.1
Name: colmap-wrapper
Version: 1.1.5
Summary: COLMAP Wrapper
Home-page: https://github.com/meyerls/colmap-wrapper
Author: Lukas Meyer
Author-email: lukas.meyer@fau.de
License: MIT
Classifier: Programming Language :: Python :: 3.8
Classifier: Programming Language :: Python :: 3.9
Classifier: License :: OSI Approved :: MIT License
Classifier: Operating System :: OS Independent
License-File: LICENSE
Requires-Dist: numpy
Requires-Dist: pyexiftool
Requires-Dist: open3d
Requires-Dist: pyquaternion
Requires-Dist: matplotlib
Requires-Dist: tqdm
Requires-Dist: wget
Requires-Dist: pycolmap
